[{"R":4.0,"Fantasy Team":"Mind Goblins","Name":"Nikola Jokic","Pos":"C","Team":"DEN","GP":"#00ff00","MPG":"#30ff30","PTS":"#00ff00","AST":"#00ff00","REB":"#00ff00","STL":"#00ff00","BLK":"#bfffbf","TO":"#ff0000","FGM":"#00ff00","FGA":"#00ff00","FG%":"#00ff00","FTM":"#00ff00","FTA":"#19ff19","FT%":"#44ff44","3PTM":"#ffbaba","3PTA":"#fed3d3","3PT%":"#ff9696","Z":"#00ff00"},{"R":1.0,"Fantasy Team":"Mind Goblins","Name":"Anthony Davis","Pos":"PF","Team":"LAL","GP":"#ff3a3a","MPG":"#1eff1e","PTS":"#00ff00","AST":"#ffbcbc","REB":"#00ff00","STL":"#00ff00","BLK":"#00ff00","TO":"#ffd8d8","FGM":"#00fe00","FGA":"#00ff00","FG%":"#00ff00","FTM":"#00ff00","FTA":"#00ff00","FT%":"#07ff07","3PTM":"#ff4c4c","3PTA":"#ff6b6b","3PT%":"#ff6666","Z":"#00ff00"},{"R":66.0,"Fantasy Team":"Mind Goblins","Name":"Domantas Sabonis","Pos":"PF","Team":"IND","GP":"#ff0000","MPG":"#0fff0f","PTS":"#f7fff7","AST":"#9eff9e","REB":"#00fe00","STL":"#ff5151","BLK":"#ff9999","TO":"#ff5b5b","FGM":"#afffaf","FGA":"#ffe8e8","FG%":"#00ff00","FTM":"#e0ffe0","FTA":"#b5feb5","FT%":"#ff1616","3PTM":"#ff0000","3PTA":"#ff0000","3PT%":"#ff9e9e","Z":"#feeded"},{"R":19.0,"Fantasy Team":"Mind Goblins","Name":"Chris Paul","Pos":"PG","Team":"PHO","GP":"#ff8484","MPG":"#8cff8c","PTS":"#ffffff","AST":"#00ff00","REB":"#ffa5a5","STL":"#00fe00","BLK":"#ff1919","TO":"#ffcccc","FGM":"#ffe0e0","FGA":"#ffeaea","FG%":"#fef4f4","FTM":"#ceffce","FTA":"#fff9f9","FT%":"#00ff00","3PTM":"#c9ffc9","3PTA":"#b7ffb7","3PT%":"#ffb7b7","Z":"#00ff00"},{"R":85.0,"Fantasy Team":"Mind Goblins","Name":"Jaylen Brown","Pos":"SG","Team":"BOS","GP":"#ff0000","MPG":"#1eff1e","PTS":"#bfffbf","AST":"#ff4242","REB":"#ffffff","STL":"#edfeed","BLK":"#ff6d6d","TO":"#ffffff","FGM":"#a5ffa5","FGA":"#b7ffb7","FG%":"#d3fed3","FTM":"#ffe2e2","FTA":"#f4fef4","FT%":"#ff3535","3PTM":"#b7ffb7","3PTA":"#b5feb5","3PT%":"#9bff9b","Z":"#ff8c8c"},{"R":65.0,"Fantasy Team":"Mind Goblins","Name":"Malcolm Brogdon","Pos":"PG","Team":"IND","GP":"#ff3a3a","MPG":"#00ff00","PTS":"#e2ffe2","AST":"#00ff00","REB":"#ffbaba","STL":"#ff5b5b","BLK":"#ff1919","TO":"#ff8484","FGM":"#d1ffd1","FGA":"#a5ffa5","FG%":"#ff8282","FTM":"#edfeed","FTA":"#ffdbdb","FT%":"#00ff00","3PTM":"#ffcece","3PTA":"#ffffff","3PT%":"#ff0000","Z":"#fff2f2"},{"R":41.0,"Fantasy Team":"Mind Goblins","Name":"Kristaps Porzingis","Pos":"C","Team":"DAL","GP":"#fe0000","MPG":"#3aff3a","PTS":"#c6ffc6","AST":"#ff0505","REB":"#42ff42","STL":"#ff1919","BLK":"#00fe00","TO":"#63ff63","FGM":"#e0ffe0","FGA":"#8cff8c","FG%":"#ff0a0a","FTM":"#c9ffc9","FTA":"#c1ffc1","FT%":"#ffe5e5","3PTM":"#89ff89","3PTA":"#6dff6d","3PT%":"#ffa3a3","Z":"#91ff91"},{"R":87.0,"Fantasy Team":"Mind Goblins","Name":"Derrick White","Pos":"PG","Team":"SAS","GP":"#9bff9b","MPG":"#ff2626","PTS":"#ff1919","AST":"#f2fff2","REB":"#ff3232","STL":"#ff3a3a","BLK":"#9bff9b","TO":"#2dff2d","FGM":"#fe0000","FGA":"#ff0000","FG%":"#ffd8d8","FTM":"#feb5b5","FTA":"#ff9999","FT%":"#75ff75","3PTM":"#ff5656","3PTA":"#ff6060","3PT%":"#fff9f9","Z":"#ff7f7f"},{"R":71.0,"Fantasy Team":"Mind Goblins","Name":"Mike Conley","Pos":"PG","Team":"UTA","GP":"#ff0000","MPG":"#bcffbc","PTS":"#ddffdd","AST":"#14ff14","REB":"#ff0505","STL":"#f7fff7","BLK":"#ff1919","TO":"#a8ffa8","FGM":"#ffeaea","FGA":"#c1ffc1","FG%":"#ff0000","FTM":"#9bff9b","FTA":"#b2ffb2","FT%":"#91ff91","3PTM":"#82ff82","3PTA":"#6dff6d","3PT%":"#f9fff9","Z":"#ffc6c6"},{"R":72.0,"Fantasy Team":"Mind Goblins","Name":"Tyler Herro","Pos":"SG","Team":"MIA","GP":"#9bff9b","MPG":"#bcffbc","PTS":"#e5ffe5","AST":"#ffc9c9","REB":"#ff9696","STL":"#ffc6c6","BLK":"#ff1e1e","TO":"#bfffbf","FGM":"#d6ffd6","FGA":"#8cff8c","FG%":"#ff0a0a","FTM":"#ff4949","FTA":"#ff3030","FT%":"#91ff91","3PTM":"#00fe00","3PTA":"#00ff00","3PT%":"#00fe00","Z":"#ffc4c4"},{"R":76.0,"Fantasy Team":"Mind Goblins","Name":"Miles Bridges","Pos":"SF","Team":"CHA","GP":"#00ff00","MPG":"#b2ffb2","PTS":"#ff8989","AST":"#ff4242","REB":"#d1ffd1","STL":"#ffa8a8","BLK":"#afffaf","TO":"#47ff47","FGM":"#ffa8a8","FGA":"#ffd6d6","FG%":"#ff6666","FTM":"#ff3d3d","FTA":"#ff3535","FT%":"#fcfffc","3PTM":"#fef4f4","3PTA":"#d6ffd6","3PT%":"#ff0000","Z":"#ffadad"},{"R":96.0,"Fantasy Team":"Mind Goblins","Name":"Mo Bamba","Pos":"C","Team":"ORL","GP":"#e5ffe5","MPG":"#ff0000","PTS":"#ff0000","AST":"#ff0000","REB":"#9eff9e","STL":"#ff0000","BLK":"#00ff00","TO":"#00ff00","FGM":"#ff0000","FGA":"#ff0000","FG%":"#fff9f9","FTM":"#ff0000","FTA":"#ff0000","FT%":"#ff7777","3PTM":"#ff2323","3PTA":"#ff3535","3PT%":"#ffbaba","Z":"#ff6060"},{"R":null,"Fantasy Team":"Mind Goblins","Name":"Desmond Bane","Pos":"SG","Team":"MEM","GP":"#ffffff","MPG":"#ffffff","PTS":"#ffffff","AST":"#ffffff","REB":"#ffffff","STL":"#ffffff","BLK":"#ffffff","TO":"#ffffff","FGM":"#ffffff","FGA":"#ffffff","FG%":"#ffffff","FTM":"#ffffff","FTA":"#ffffff","FT%":"#ffffff","3PTM":"#ffffff","3PTA":"#ffffff","3PT%":"#ffffff","Z":"#ffffff"},{"R":null,"Fantasy Team":"Mind Goblins","Name":"Franz Wagner","Pos":"SF","Team":"ORL","GP":"#ffffff","MPG":"#ffffff","PTS":"#ffffff","AST":"#ffffff","REB":"#ffffff","STL":"#ffffff","BLK":"#ffffff","TO":"#ffffff","FGM":"#ffffff","FGA":"#ffffff","FG%":"#ffffff","FTM":"#ffffff","FTA":"#ffffff","FT%":"#ffffff","3PTM":"#ffffff","3PTA":"#ffffff","3PT%":"#ffffff","Z":"#ffffff"},{"R":26.0,"Fantasy Team":"FULLA Shoota","Name":"LeBron James","Pos":"SF","Team":"LAL","GP":"#ffcece","MPG":"#4fff4f","PTS":"#00ff00","AST":"#00ff00","REB":"#60ff60","STL":"#7fff7f","BLK":"#ffd1d1","TO":"#ff0000","FGM":"#00ff00","FGA":"#00fe00","FG%":"#00ff00","FTM":"#68ff68","FTA":"#11ff11","FT%":"#fe0000","3PTM":"#bcffbc","3PTA":"#93ff93","3PT%":"#ff5151","Z":"#23ff23"},{"R":12.0,"Fantasy Team":"FULLA Shoota","Name":"Paul George","Pos":"SF","Team":"LAC","GP":"#e5ffe5","MPG":"#3fff3f","PTS":"#00ff00","AST":"#efffef","REB":"#b2ffb2","STL":"#00ff00","BLK":"#ffa5a5","TO":"#ff4444","FGM":"#2dff2d","FGA":"#00fe00","FG%":"#ff0000","FTM":"#00ff00","FTA":"#2bff2b","FT%":"#00ff00","3PTM":"#00ff00","3PTA":"#00ff00","3PT%":"#00ff00","Z":"#00ff00"},{"R":14.0,"Fantasy Team":"FULLA Shoota","Name":"Devin Booker","Pos":"SG","Team":"PHO","GP":"#4fff4f","MPG":"#00ff00","PTS":"#00fe00","AST":"#00ff00","REB":"#ff7777","STL":"#ffc6c6","BLK":"#ff5151","TO":"#ff0000","FGM":"#00ff00","FGA":"#00ff00","FG%":"#c1ffc1","FTM":"#00ff00","FTA":"#00ff00","FT%":"#00ff00","3PTM":"#11ff11","3PTA":"#00ff00","3PT%":"#ff7f7f","Z":"#00ff00"},{"R":21.0,"Fantasy Team":"FULLA Shoota","Name":"Deandre Ayton","Pos":"C","Team":"PHO","GP":"#e5ffe5","MPG":"#70ff70","PTS":"#47ff47","AST":"#ff3a3a","REB":"#00fe00","STL":"#ff7070","BLK":"#00ff00","TO":"#fef4f4","FGM":"#00ff00","FGA":"#66ff66","FG%":"#00fe00","FTM":"#c4ffc4","FTA":"#b5feb5","FT%":"#ffc1c1","3PTM":"#ff0000","3PTA":"#ff0000","3PT%":"#f9fff9","Z":"#00ff00"},{"R":25.0,"Fantasy Team":"FULLA Shoota","Name":"Tobias Harris","Pos":"SF","Team":"PHL","GP":"#00ff00","MPG":"#0fff0f","PTS":"#00ff00","AST":"#ffc4c4","REB":"#66ff66","STL":"#ff5151","BLK":"#ffbaba","TO":"#9eff9e","FGM":"#00fe00","FGA":"#00ff00","FG%":"#c4ffc4","FTM":"#feeded","FTA":"#fed3d3","FT%":"#77ff77","3PTM":"#16ff16","3PTA":"#21ff21","3PT%":"#21ff21","Z":"#1eff1e"},{"R":43.0,"Fantasy Team":"FULLA Shoota","Name":"D'Angelo Russell","Pos":"PG","Team":"MIN","GP":"#ff8484","MPG":"#54ff54","PTS":"#05ff05","AST":"#00ff00","REB":"#ff6b6b","STL":"#96ff96","BLK":"#ff4949","TO":"#ff0000","FGM":"#00ff00","FGA":"#00ff00","FG%":"#ff0f0f","FTM":"#fef4f4","FTA":"#ffe2e2","FT%":"#8cff8c","3PTM":"#00ff00","3PTA":"#00ff00","3PT%":"#ffe8e8","Z":"#9eff9e"},{"R":null,"Fantasy Team":"FULLA Shoota","Name":"Klay Thompson","Pos":"SG","Team":"GSW","GP":"#ffffff","MPG":"#ffffff","PTS":"#ffffff","AST":"#ffffff","REB":"#ffffff","STL":"#ffffff","BLK":"#ffffff","TO":"#ffffff","FGM":"#ffffff","FGA":"#ffffff","FG%":"#ffffff","FTM":"#ffffff","FTA":"#ffffff","FT%":"#ffffff","3PTM":"#ffffff","3PTA":"#ffffff","3PT%":"#ffffff","Z":"#ffffff"},{"R":48.0,"Fantasy Team":"FULLA Shoota","Name":"Jonas Valanciunas","Pos":"C","Team":"NOP","GP":"#ffcece","MPG":"#ff6b6b","PTS":"#ffc4c4","AST":"#ff2b2b","REB":"#00fe00","STL":"#fe0000","BLK":"#23ff23","TO":"#adffad","FGM":"#ddffdd","FGA":"#ff9696","FG%":"#00ff00","FTM":"#ff7f7f","FTA":"#ff8e8e","FT%":"#ffadad","3PTM":"#ff0000","3PTA":"#ff0000","3PT%":"#ddffdd","Z":"#bcffbc"},{"R":80.0,"Fantasy Team":"FULLA Shoota","Name":"Bojan Bogdanovic","Pos":"PF","Team":"UTA","GP":"#e5ffe5","MPG":"#7aff7a","PTS":"#baffba","AST":"#ff4444","REB":"#ff6363","STL":"#ff3030","BLK":"#ff0000","TO":"#efffef","FGM":"#e0ffe0","FGA":"#d8ffd8","FG%":"#fef4f4","FTM":"#ceffce","FTA":"#f9fff9","FT%":"#0cff0c","3PTM":"#23ff23","3PTA":"#5bff5b","3PT%":"#00ff00","Z":"#ff9e9e"},{"R":103.5,"Fantasy Team":"FULLA Shoota","Name":"Jordan Clarkson","Pos":"SG","Team":"UTA","GP":"#00ff00","MPG":"#ff0000","PTS":"#ffefef","AST":"#ff6b6b","REB":"#ff0707","STL":"#ff5151","BLK":"#ff2626","TO":"#7aff7a","FGM":"#efffef","FGA":"#d8ffd8","FG%":"#ffbfbf","FTM":"#ff7272","FTA":"#ff5e5e","FT%":"#b2ffb2","3PTM":"#adffad","3PTA":"#87ff87","3PT%":"#ff4c4c","Z":"#ff3a3a"},{"R":108.0,"Fantasy Team":"FULLA Shoota","Name":"Harrison Barnes","Pos":"SF","Team":"SAC","GP":"#00ff00","MPG":"#c1ffc1","PTS":"#ffcccc","AST":"#ff4747","REB":"#ffaaaa","STL":"#ff0505","BLK":"#ff2626","TO":"#1eff1e","FGM":"#ffafaf","FGA":"#ffdbdb","FG%":"#ff6666","FTM":"#ffffff","FTA":"#fff2f2","FT%":"#c1ffc1","3PTM":"#efffef","3PTA":"#f9fff9","3PT%":"#9eff9e","Z":"#ff2626"},{"R":110.0,"Fantasy Team":"FULLA Shoota","Name":"Derrick Rose","Pos":"PG","Team":"NYK","GP":"#ff0000","MPG":"#ff3a3a","PTS":"#ffd8d8","AST":"#a5ffa5","REB":"#ff0000","STL":"#ff0000","BLK":"#ff3d3d","TO":"#e2ffe2","FGM":"#ddffdd","FGA":"#efffef","FG%":"#d6ffd6","FTM":"#ff8e8e","FTA":"#ff7070","FT%":"#72ff72","3PTM":"#ff3232","3PTA":"#ff5151","3PT%":"#ff7c7c","Z":"#ff0a0a"},{"R":117.5,"Fantasy Team":"FULLA Shoota","Name":"Alex Caruso","Pos":"PG","Team":"CHI","GP":"#ffcece","MPG":"#ff0000","PTS":"#ff0000","AST":"#ff6d6d","REB":"#ff0000","STL":"#7fff7f","BLK":"#ff7575","TO":"#05ff05","FGM":"#ff0000","FGA":"#ff0000","FG%":"#ffa5a5","FTM":"#ff1414","FTA":"#ff1111","FT%":"#ffe8e8","3PTM":"#ff2b2b","3PTA":"#ff2828","3PT%":"#d1ffd1","Z":"#ff0000"},{"R":null,"Fantasy Team":"FULLA Shoota","Name":"Chris Duarte","Pos":"SG","Team":"IND","GP":"#ffffff","MPG":"#ffffff","PTS":"#ffffff","AST":"#ffffff","REB":"#ffffff","STL":"#ffffff","BLK":"#ffffff","TO":"#ffffff","FGM":"#ffffff","FGA":"#ffffff","FG%":"#ffffff","FTM":"#ffffff","FTA":"#ffffff","FT%":"#ffffff","3PTM":"#ffffff","3PTA":"#ffffff","3PT%":"#ffffff","Z":"#ffffff"},{"R":94.5,"Fantasy Team":"Los Angeles Better Than U's","Name":"LaMelo Ball","Pos":"PG","Team":"CHA","GP":"#4fff4f","MPG":"#feeded","PTS":"#ffe0e0","AST":"#00ff00","REB":"#ff6666","STL":"#a0ffa0","BLK":"#ff7a7a","TO":"#ff0c0c","FGM":"#ffc6c6","FGA":"#e2ffe2","FG%":"#ff0000","FTM":"#ffd1d1","FTA":"#fff2f2","FT%":"#ff5b5b","3PTM":"#82ff82","3PTA":"#ff2828","3PT%":"#ffc1c1","Z":"#ff6666"},{"R":70.0,"Fantasy Team":"Los Angeles Better Than U's","Name":"Lonzo Ball","Pos":"PG","Team":"CHI","GP":"#ff8484","MPG":"#70ff70","PTS":"#ff2626","AST":"#00ff00","REB":"#efffef","STL":"#00fe00","BLK":"#ffc9c9","TO":"#ff3f3f","FGM":"#ff3232","FGA":"#ff7a7a","FG%":"#ff0000","FTM":"#ff0000","FTA":"#ff0000","FT%":"#ff2323","3PTM":"#89ff89","3PTA":"#6dff6d","3PT%":"#ffa3a3","Z":"#ffc9c9"},{"R":51.5,"Fantasy Team":"Los Angeles Better Than U's","Name":"Michael Porter Jr.","Pos":"SF","Team":"DEN","GP":"#ff8484","MPG":"#ff7272","PTS":"#fffcfc","AST":"#ff0707","REB":"#99ff99","STL":"#ff6666","BLK":"#dbffdb","TO":"#51ff51","FGM":"#fff9f9","FGA":"#ffdddd","FG%":"#aaffaa","FTM":"#ffbcbc","FTA":"#feb5b5","FT%":"#e2ffe2","3PTM":"#7cff7c","3PTA":"#afffaf","3PT%":"#00ff00","Z":"#ccffcc"},{"R":54.5,"Fantasy Team":"Los Angeles Better Than U's","Name":"Clint Capela","Pos":"C","Team":"ATL","GP":"#e5ffe5","MPG":"#e2ffe2","PTS":"#ff9b9b","AST":"#ff0000","REB":"#00ff00","STL":"#ff3030","BLK":"#00ff00","TO":"#44ff44","FGM":"#efffef","FGA":"#ff4949","FG%":"#00ff00","FTM":"#ff5e5e","FTA":"#feb5b5","FT%":"#fe0000","3PTM":"#ff0000","3PTA":"#fe0000","3PT%":"#baffba","Z":"#dbffdb"},{"R":107.0,"Fantasy Team":"Los Angeles Better Than U's","Name":"Anthony Edwards","Pos":"SG","Team":"MIN","GP":"#4fff4f","MPG":"#ccffcc","PTS":"#ffcccc","AST":"#ff7070","REB":"#ff7777","STL":"#a0ffa0","BLK":"#ffdddd","TO":"#e2ffe2","FGM":"#ff8484","FGA":"#ffcccc","FG%":"#ff0a0a","FTM":"#75ff75","FTA":"#5eff5e","FT%":"#ff9191","3PTM":"#ffd8d8","3PTA":"#ff0000","3PT%":"#ff9e9e","Z":"#ff2828"},{"R":53.0,"Fantasy Team":"Los Angeles Better Than U's","Name":"Richaun Holmes","Pos":"C","Team":"SAC","GP":"#ffcece","MPG":"#ff0000","PTS":"#ff1616","AST":"#ff0000","REB":"#84ff84","STL":"#ffb2b2","BLK":"#00ff00","TO":"#00ff00","FGM":"#ff5151","FGA":"#ff0000","FG%":"#00ff00","FTM":"#ff5b5b","FTA":"#ff5656","FT%":"#fcfffc","3PTM":"#ff0000","3PTA":"#fe0000","3PT%":"#baffba","Z":"#ceffce"},{"R":67.0,"Fantasy Team":"Los Angeles Better Than U's","Name":"Jaren Jackson Jr.","Pos":"PF","Team":"MEM","GP":"#ff0000","MPG":"#ffdddd","PTS":"#ffd6d6","AST":"#ff0000","REB":"#ff8989","STL":"#ff3a3a","BLK":"#00ff00","TO":"#84ff84","FGM":"#fed3d3","FGA":"#ffd1d1","FG%":"#fff7f7","FTM":"#ff8e8e","FTA":"#ff9e9e","FT%":"#ff9393","3PTM":"#7cff7c","3PTA":"#91ff91","3PT%":"#3dff3d","Z":"#ffdbdb"},{"R":40.0,"Fantasy Team":"Los Angeles Better Than U's","Name":"Mikal Bridges","Pos":"SF","Team":"PHO","GP":"#00ff00","MPG":"#b7ffb7","PTS":"#ff0000","AST":"#ff6363","REB":"#ff8282","STL":"#00ff00","BLK":"#ffe5e5","TO":"#00ff00","FGM":"#ff0000","FGA":"#ff0000","FG%":"#c9ffc9","FTM":"#ff3a3a","FTA":"#ff2626","FT%":"#b2ffb2","3PTM":"#ffa5a5","3PTA":"#ffbaba","3PT%":"#ffa3a3","Z":"#8eff8e"},{"R":128.0,"Fantasy Team":"Los Angeles Better Than U's","Name":"Robert Williams III","Pos":"C","Team":"BOS","GP":"#ff0000","MPG":"#ff0000","PTS":"#fe0000","AST":"#ff0000","REB":"#ff1414","STL":"#ff0000","BLK":"#54ff54","TO":"#00ff00","FGM":"#ff0000","FGA":"#ff0000","FG%":"#60ff60","FTM":"#ff0000","FTA":"#fe0000","FT%":"#ff8484","3PTM":"#ff0000","3PTA":"#fe0000","3PT%":"#baffba","Z":"#ff0000"},{"R":null,"Fantasy Team":"Los Angeles Better Than U's","Name":"Scottie Barnes","Pos":"PF","Team":"TOR","GP":"#ffffff","MPG":"#ffffff","PTS":"#ffffff","AST":"#ffffff","REB":"#ffffff","STL":"#ffffff","BLK":"#ffffff","TO":"#ffffff","FGM":"#ffffff","FGA":"#ffffff","FG%":"#ffffff","FTM":"#ffffff","FTA":"#ffffff","FT%":"#ffffff","3PTM":"#ffffff","3PTA":"#ffffff","3PT%":"#ffffff","Z":"#ffffff"},{"R":null,"Fantasy Team":"Los Angeles Better Than U's","Name":"Evan Mobley","Pos":"PF","Team":"CLE","GP":"#ffffff","MPG":"#ffffff","PTS":"#ffffff","AST":"#ffffff","REB":"#ffffff","STL":"#ffffff","BLK":"#ffffff","TO":"#ffffff","FGM":"#ffffff","FGA":"#ffffff","FG%":"#ffffff","FTM":"#ffffff","FTA":"#ffffff","FT%":"#ffffff","3PTM":"#ffffff","3PTA":"#ffffff","3PT%":"#ffffff","Z":"#ffffff"},{"R":125.0,"Fantasy Team":"Los Angeles Better Than U's","Name":"Kyle Kuzma","Pos":"PF","Team":"WAS","GP":"#ffcece","MPG":"#ff0505","PTS":"#ff7272","AST":"#ff1414","REB":"#ff8989","STL":"#fe0000","BLK":"#ff7575","TO":"#5bff5b","FGM":"#ff8282","FGA":"#ffa5a5","FG%":"#ff7070","FTM":"#ff5e5e","FTA":"#ff6b6b","FT%":"#ffa3a3","3PTM":"#ffc6c6","3PTA":"#f2fff2","3PT%":"#ff0000","Z":"#ff0000"},{"R":null,"Fantasy Team":"Los Angeles Better Than U's","Name":"Josh Giddey","Pos":"PG","Team":"OKC","GP":"#ffffff","MPG":"#ffffff","PTS":"#ffffff","AST":"#ffffff","REB":"#ffffff","STL":"#ffffff","BLK":"#ffffff","TO":"#ffffff","FGM":"#ffffff","FGA":"#ffffff","FG%":"#ffffff","FTM":"#ffffff","FTA":"#ffffff","FT%":"#ffffff","3PTM":"#ffffff","3PTA":"#ffffff","3PT%":"#ffffff","Z":"#ffffff"},{"R":81.0,"Fantasy Team":"Los Angeles Better Than U's","Name":"Duncan Robinson","Pos":"SG","Team":"MIA","GP":"#9bff9b","MPG":"#ffd8d8","PTS":"#ff6868","AST":"#ff0202","REB":"#ff1616","STL":"#ff0000","BLK":"#ff1e1e","TO":"#00ff00","FGM":"#ff3030","FGA":"#ff3030","FG%":"#fff9f9","FTM":"#ff0000","FTA":"#ff0000","FT%":"#c1ffc1","3PTM":"#00ff00","3PTA":"#00ff00","3PT%":"#00ff00","Z":"#ff9999"},{"R":7.0,"Fantasy Team":"Big Tech","Name":"Kevin Durant","Pos":"SF","Team":"BKN","GP":"#e5ffe5","MPG":"#3aff3a","PTS":"#00fe00","AST":"#2dff2d","REB":"#b2ffb2","STL":"#ff7070","BLK":"#00ff00","TO":"#ff2828","FGM":"#00fe00","FGA":"#05ff05","FG%":"#00ff00","FTM":"#00ff00","FTA":"#00ff00","FT%":"#00ff00","3PTM":"#b5feb5","3PTA":"#b2ffb2","3PT%":"#9bff9b","Z":"#00ff00"},{"R":3.0,"Fantasy Team":"Big Tech","Name":"Karl-Anthony Towns","Pos":"C","Team":"MIN","GP":"#05ff05","MPG":"#14ff14","PTS":"#00ff00","AST":"#f2fff2","REB":"#00ff00","STL":"#fed3d3","BLK":"#00ff00","TO":"#ff0000","FGM":"#00ff00","FGA":"#00ff00","FG%":"#00ff00","FTM":"#00ff00","FTA":"#00ff00","FT%":"#59ff59","3PTM":"#02ff02","3PTA":"#35ff35","3PT%":"#00ff00","Z":"#00ff00"},{"R":45.0,"Fantasy Team":"Big Tech","Name":"Russell Westbrook","Pos":"PG","Team":"LAL","GP":"#ffcece","MPG":"#44ff44","PTS":"#00fe00","AST":"#00ff00","REB":"#35ff35","STL":"#00ff00","BLK":"#ff4949","TO":"#ff0000","FGM":"#00ff00","FGA":"#00ff00","FG%":"#ffa0a0","FTM":"#2dff2d","FTA":"#07ff07","FT%":"#ff5454","3PTM":"#ff6868","3PTA":"#fed3d3","3PT%":"#ff0000","Z":"#b2ffb2"},{"R":51.5,"Fantasy Team":"Big Tech","Name":"Zach LaVine","Pos":"SG","Team":"CHI","GP":"#ff0000","MPG":"#14ff14","PTS":"#00ff00","AST":"#d3fed3","REB":"#ff8787","STL":"#28ff28","BLK":"#ff9999","TO":"#ff0000","FGM":"#05ff05","FGA":"#00ff00","FG%":"#ff6060","FTM":"#56ff56","FTA":"#5eff5e","FT%":"#a8ffa8","3PTM":"#00ff00","3PTA":"#00ff00","3PT%":"#8eff8e","Z":"#ccffcc"},{"R":49.5,"Fantasy Team":"Big Tech","Name":"Jerami Grant","Pos":"SF","Team":"DET","GP":"#05ff05","MPG":"#44ff44","PTS":"#ffeaea","AST":"#ff0000","REB":"#77ff77","STL":"#ff9191","BLK":"#07ff07","TO":"#00ff00","FGM":"#ffe8e8","FGA":"#ffd1d1","FG%":"#aaffaa","FTM":"#ffe5e5","FTA":"#efffef","FT%":"#ff3232","3PTM":"#eaffea","3PTA":"#f4fef4","3PT%":"#54ff54","Z":"#c1ffc1"},{"R":32.0,"Fantasy Team":"Big Tech","Name":"Kyle Lowry","Pos":"PG","Team":"MIA","GP":"#9bff9b","MPG":"#44ff44","PTS":"#ffffff","AST":"#00ff00","REB":"#ffaaaa","STL":"#1eff1e","BLK":"#ff7a7a","TO":"#ff3535","FGM":"#ff9999","FGA":"#ffeaea","FG%":"#ff0000","FTM":"#a8ffa8","FTA":"#ceffce","FT%":"#16ff16","3PTM":"#00ff00","3PTA":"#00ff00","3PT%":"#ff7777","Z":"#51ff51"},{"R":112.0,"Fantasy Team":"Big Tech","Name":"Spencer Dinwiddie","Pos":"SG","Team":"WAS","GP":"#9bff9b","MPG":"#ff5656","PTS":"#fff2f2","AST":"#23ff23","REB":"#ff0000","STL":"#ff0000","BLK":"#ff5151","TO":"#ffe8e8","FGM":"#ffa0a0","FGA":"#ffefef","FG%":"#ff0000","FTM":"#56ff56","FTA":"#4fff4f","FT%":"#f7fff7","3PTM":"#efffef","3PTA":"#a0ffa0","3PT%":"#fe0000","Z":"#ff0000"},{"R":130.0,"Fantasy Team":"Big Tech","Name":"Keldon Johnson","Pos":"SF","Team":"SAS","GP":"#ff0000","MPG":"#ff0000","PTS":"#fe0000","AST":"#ff0000","REB":"#ff0000","STL":"#ff5151","BLK":"#ff1919","TO":"#00ff00","FGM":"#fe0000","FGA":"#fe0000","FG%":"#efffef","FTM":"#ff1919","FTA":"#ff1e1e","FT%":"#ffbcbc","3PTM":"#ff0000","3PTA":"#ff0000","3PT%":"#d3fed3","Z":"#ff0000"},{"R":100.5,"Fantasy Team":"Big Tech","Name":"Norman Powell","Pos":"SG","Team":"POR","GP":"#ffcece","MPG":"#ff0000","PTS":"#ff4f4f","AST":"#ff2b2b","REB":"#ff0505","STL":"#fff2f2","BLK":"#ff4949","TO":"#3aff3a","FGM":"#ff4949","FGA":"#ff3838","FG%":"#e2ffe2","FTM":"#ff4747","FTA":"#ff3232","FT%":"#bfffbf","3PTM":"#fcfffc","3PTA":"#fff9f9","3PT%":"#56ff56","Z":"#ff4747"},{"R":105.0,"Fantasy Team":"Big Tech","Name":"Tim Hardaway Jr.","Pos":"SG","Team":"DAL","GP":"#e5ffe5","MPG":"#fff9f9","PTS":"#fff7f7","AST":"#ff5b5b","REB":"#ff1c1c","STL":"#ff3030","BLK":"#ff0000","TO":"#23ff23","FGM":"#fed3d3","FGA":"#d8ffd8","FG%":"#ff0000","FTM":"#ffbcbc","FTA":"#ffaaaa","FT%":"#b5feb5","3PTM":"#00ff00","3PTA":"#00ff00","3PT%":"#fff7f7","Z":"#ff3232"},{"R":99.0,"Fantasy Team":"Big Tech","Name":"Wendell Carter Jr.","Pos":"C","Team":"ORL","GP":"#ff0000","MPG":"#e8ffe8","PTS":"#ff0f0f","AST":"#ff0000","REB":"#05ff05","STL":"#ff3a3a","BLK":"#77ff77","TO":"#84ff84","FGM":"#ff1919","FGA":"#ff0000","FG%":"#87ff87","FTM":"#ffa5a5","FTA":"#ffb2b2","FT%":"#ffa5a5","3PTM":"#fe0000","3PTA":"#ff0000","3PT%":"#ffdddd","Z":"#ff4f4f"},{"R":46.5,"Fantasy Team":"Big Tech","Name":"Al Horford","Pos":"C","Team":"BOS","GP":"#9bff9b","MPG":"#e8ffe8","PTS":"#ff6363","AST":"#baffba","REB":"#8cff8c","STL":"#ff7c7c","BLK":"#3fff3f","TO":"#47ff47","FGM":"#ff9b9b","FGA":"#ff9393","FG%":"#ddffdd","FTM":"#ff0000","FTA":"#ff0000","FT%":"#fff7f7","3PTM":"#feb5b5","3PTA":"#ffcccc","3PT%":"#ff9b9b","Z":"#b5feb5"},{"R":127.0,"Fantasy Team":"Big Tech","Name":"Nickeil Alexander-Walker","Pos":"SG","Team":"NOP","GP":"#ff3a3a","MPG":"#ff0000","PTS":"#ff0000","AST":"#ffbcbc","REB":"#ff1e1e","STL":"#fe0000","BLK":"#ff4242","TO":"#84ff84","FGM":"#ff0000","FGA":"#ff3030","FG%":"#ff1e1e","FTM":"#ff0000","FTA":"#ff0000","FT%":"#ffc4c4","3PTM":"#e2ffe2","3PTA":"#d3fed3","3PT%":"#ffbfbf","Z":"#fe0000"},{"R":2.0,"Fantasy Team":"Washington D.C. Hoopers","Name":"James Harden","Pos":"SG","Team":"BKN","GP":"#05ff05","MPG":"#14ff14","PTS":"#00fe00","AST":"#00fe00","REB":"#d6ffd6","STL":"#00ff00","BLK":"#bfffbf","TO":"#ff0000","FGM":"#00ff00","FGA":"#00fe00","FG%":"#ff0000","FTM":"#00ff00","FTA":"#00ff00","FT%":"#00ff00","3PTM":"#00fe00","3PTA":"#00fe00","3PT%":"#ff1111","Z":"#00ff00"},{"R":18.0,"Fantasy Team":"Washington D.C. Hoopers","Name":"Bradley Beal","Pos":"SG","Team":"WAS","GP":"#05ff05","MPG":"#14ff14","PTS":"#00ff00","AST":"#70ff70","REB":"#ff7c7c","STL":"#54ff54","BLK":"#ff8282","TO":"#ff0000","FGM":"#00ff00","FGA":"#00ff00","FG%":"#feeded","FTM":"#00ff00","FTA":"#00ff00","FT%":"#00ff00","3PTM":"#00ff00","3PTA":"#00ff00","3PT%":"#ff6363","Z":"#00ff00"},{"R":34.0,"Fantasy Team":"Washington D.C. Hoopers","Name":"Donovan Mitchell","Pos":"SG","Team":"UTA","GP":"#00ff00","MPG":"#35ff35","PTS":"#00fe00","AST":"#afffaf","REB":"#ff8484","STL":"#3fff3f","BLK":"#ff5151","TO":"#ff1111","FGM":"#00fe00","FGA":"#00ff00","FG%":"#ff3d3d","FTM":"#00ff00","FTA":"#0cff0c","FT%":"#42ff42","3PTM":"#00fe00","3PTA":"#00ff00","3PT%":"#ff6666","Z":"#5bff5b"},{"R":31.0,"Fantasy Team":"Washington D.C. Hoopers","Name":"Rudy Gobert","Pos":"C","Team":"UTA","GP":"#e5ffe5","MPG":"#5bff5b","PTS":"#ffbaba","AST":"#ff2323","REB":"#00fe00","STL":"#ff7070","BLK":"#00ff00","TO":"#b5feb5","FGM":"#ffcece","FGA":"#ff0000","FG%":"#00ff00","FTM":"#93ff93","FTA":"#07ff07","FT%":"#fe0000","3PTM":"#ff0000","3PTA":"#fe0000","3PT%":"#baffba","Z":"#4cff4c"},{"R":58.0,"Fantasy Team":"Washington D.C. Hoopers","Name":"Ja Morant","Pos":"PG","Team":"MEM","GP":"#9bff9b","MPG":"#44ff44","PTS":"#00fe00","AST":"#00ff00","REB":"#ff6060","STL":"#f7fff7","BLK":"#ff5151","TO":"#ff0000","FGM":"#00ff00","FGA":"#00ff00","FG%":"#84ff84","FTM":"#00ff00","FTA":"#00ff00","FT%":"#f4fef4","3PTM":"#ffa3a3","3PTA":"#ff9b9b","3PT%":"#a5ffa5","Z":"#f2fff2"},{"R":75.0,"Fantasy Team":"Washington D.C. Hoopers","Name":"Montrezl Harrell","Pos":"C","Team":"WAS","GP":"#00ff00","MPG":"#ff2b2b","PTS":"#ccffcc","AST":"#ff3030","REB":"#93ff93","STL":"#ff5151","BLK":"#00ff00","TO":"#99ff99","FGM":"#6dff6d","FGA":"#ffdbdb","FG%":"#00ff00","FTM":"#bcffbc","FTA":"#49ff49","FT%":"#ff0000","3PTM":"#ff0000","3PTA":"#ff0000","3PT%":"#ffd8d8","Z":"#feb5b5"},{"R":90.0,"Fantasy Team":"Washington D.C. Hoopers","Name":"Terry Rozier","Pos":"PG","Team":"CHA","GP":"#05ff05","MPG":"#ffe2e2","PTS":"#ffc4c4","AST":"#f2fff2","REB":"#ff7575","STL":"#fed3d3","BLK":"#ff1e1e","TO":"#d1ffd1","FGM":"#ffadad","FGA":"#f9fff9","FG%":"#ff0000","FTM":"#ff9393","FTA":"#ff7272","FT%":"#70ff70","3PTM":"#51ff51","3PTA":"#68ff68","3PT%":"#32ff32","Z":"#ff7575"},{"R":39.0,"Fantasy Team":"Washington D.C. Hoopers","Name":"Ben Simmons","Pos":"PG","Team":"PHL","GP":"#e5ffe5","MPG":"#00ff00","PTS":"#d6ffd6","AST":"#00fe00","REB":"#21ff21","STL":"#00ff00","BLK":"#a3ffa3","TO":"#ff0000","FGM":"#7aff7a","FGA":"#fef4f4","FG%":"#00fe00","FTM":"#c4ffc4","FTA":"#2bff2b","FT%":"#ff0000","3PTM":"#ff0000","3PTA":"#ff0000","3PT%":"#ddffdd","Z":"#87ff87"},{"R":124.0,"Fantasy Team":"Washington D.C. Hoopers","Name":"RJ Barrett","Pos":"SF","Team":"NYK","GP":"#9bff9b","MPG":"#8cff8c","PTS":"#ffeaea","AST":"#ff9b9b","REB":"#ffd8d8","STL":"#f7fff7","BLK":"#ff5151","TO":"#ffadad","FGM":"#ffe5e5","FGA":"#c6ffc6","FG%":"#ff0000","FTM":"#ceffce","FTA":"#89ff89","FT%":"#ff0000","3PTM":"#ff9b9b","3PTA":"#ffc1c1","3PT%":"#ff2121","Z":"#fe0000"},{"R":89.0,"Fantasy Team":"Washington D.C. Hoopers","Name":"Chris Boucher","Pos":"C","Team":"TOR","GP":"#ff0000","MPG":"#ff0000","PTS":"#fe0000","AST":"#ff0000","REB":"#e0ffe0","STL":"#ff0000","BLK":"#00ff00","TO":"#00ff00","FGM":"#ff0000","FGA":"#ff0000","FG%":"#ffe0e0","FTM":"#ff7272","FTA":"#ff6868","FT%":"#e8ffe8","3PTM":"#ff2323","3PTA":"#ff5454","3PT%":"#fe0000","Z":"#ff7777"},{"R":69.0,"Fantasy Team":"Washington D.C. Hoopers","Name":"Lauri Markkanen","Pos":"PF","Team":"CLE","GP":"#ff0000","MPG":"#3aff3a","PTS":"#fff2f2","AST":"#ff0c0c","REB":"#60ff60","STL":"#ff5151","BLK":"#ffc1c1","TO":"#7aff7a","FGM":"#ffd6d6","FGA":"#e2ffe2","FG%":"#ff2323","FTM":"#ffdbdb","FTA":"#ffbfbf","FT%":"#7cff7c","3PTM":"#60ff60","3PTA":"#38ff38","3PT%":"#ff2626","Z":"#fed3d3"},{"R":117.5,"Fantasy Team":"Washington D.C. Hoopers","Name":"Carmelo Anthony","Pos":"PF","Team":"LAL","GP":"#ffcece","MPG":"#ff9191","PTS":"#ff6b6b","AST":"#ff0000","REB":"#ffd1d1","STL":"#ff0000","BLK":"#ff7575","TO":"#3aff3a","FGM":"#ff7575","FGA":"#ffc1c1","FG%":"#ff0f0f","FTM":"#ff5959","FTA":"#ff4949","FT%":"#c9ffc9","3PTM":"#ffcece","3PTA":"#ffdddd","3PT%":"#ffd6d6","Z":"#ff0000"},{"R":131.0,"Fantasy Team":"Washington D.C. Hoopers","Name":"Jordan Poole","Pos":"SG","Team":"GSW","GP":"#ff3a3a","MPG":"#ff0000","PTS":"#ff0000","AST":"#ff3a3a","REB":"#ff0000","STL":"#fe0000","BLK":"#ff1919","TO":"#00ff00","FGM":"#ff0000","FGA":"#ff0000","FG%":"#ff1e1e","FTM":"#ff0c0c","FTA":"#ff0000","FT%":"#e5ffe5","3PTM":"#ff8e8e","3PTA":"#ffbfbf","3PT%":"#fe0000","Z":"#ff0000"},{"R":123.0,"Fantasy Team":"Washington D.C. Hoopers","Name":"Cole Anthony","Pos":"PG","Team":"ORL","GP":"#ff0000","MPG":"#ff2b2b","PTS":"#ff3232","AST":"#ffcccc","REB":"#ff0000","STL":"#ff9191","BLK":"#ff0000","TO":"#ffffff","FGM":"#ff1c1c","FGA":"#ff5959","FG%":"#ff3535","FTM":"#ff2b2b","FTA":"#ff2828","FT%":"#ffe5e5","3PTM":"#bcffbc","3PTA":"#ff1111","3PT%":"#efffef","Z":"#ff0000"},{"R":8.0,"Fantasy Team":"ATL Braves","Name":"Jayson Tatum","Pos":"PF","Team":"BOS","GP":"#e5ffe5","MPG":"#00ff00","PTS":"#00ff00","AST":"#f9fff9","REB":"#8eff8e","STL":"#00ff00","BLK":"#77ff77","TO":"#ffd6d6","FGM":"#00ff00","FGA":"#00ff00","FG%":"#ff4f4f","FTM":"#00ff00","FTA":"#00ff00","FT%":"#68ff68","3PTM":"#00ff00","3PTA":"#00ff00","3PT%":"#00ff00","Z":"#00ff00"},{"R":23.0,"Fantasy Team":"ATL Braves","Name":"Trae Young","Pos":"PG","Team":"ATL","GP":"#e5ffe5","MPG":"#00ff00","PTS":"#00ff00","AST":"#00ff00","REB":"#ff7575","STL":"#c1ffc1","BLK":"#ff0000","TO":"#ff0000","FGM":"#00ff00","FGA":"#00ff00","FG%":"#ff0000","FTM":"#00ff00","FTA":"#00ff00","FT%":"#00ff00","3PTM":"#00ff00","3PTA":"#00ff00","3PT%":"#ff4949","Z":"#0cff0c"},{"R":10.0,"Fantasy Team":"ATL Braves","Name":"Jimmy Butler","Pos":"SF","Team":"MIA","GP":"#4fff4f","MPG":"#1eff1e","PTS":"#3dff3d","AST":"#3dff3d","REB":"#e0ffe0","STL":"#00fe00","BLK":"#ffadad","TO":"#e2ffe2","FGM":"#96ff96","FGA":"#89ff89","FG%":"#fef4f4","FTM":"#00ff00","FTA":"#00ff00","FT%":"#00ff00","3PTM":"#ff7777","3PTA":"#ffa0a0","3PT%":"#ff3d3d","Z":"#00ff00"},{"R":46.5,"Fantasy Team":"ATL Braves","Name":"Christian Wood","Pos":"C","Team":"HOU","GP":"#ffcece","MPG":"#ffffff","PTS":"#d3fed3","AST":"#ff0000","REB":"#00ff00","STL":"#ff2626","BLK":"#23ff23","TO":"#ccffcc","FGM":"#e2ffe2","FGA":"#ffa5a5","FG%":"#00ff00","FTM":"#63ff63","FTA":"#3fff3f","FT%":"#ff6060","3PTM":"#ff8787","3PTA":"#ff8787","3PT%":"#dbffdb","Z":"#b5feb5"},{"R":61.5,"Fantasy Team":"ATL Braves","Name":"Buddy Hield","Pos":"SG","Team":"SAC","GP":"#00ff00","MPG":"#ffb7b7","PTS":"#b5feb5","AST":"#ff9b9b","REB":"#ff9696","STL":"#ffdddd","BLK":"#ff5151","TO":"#ffeaea","FGM":"#a8ffa8","FGA":"#66ff66","FG%":"#ff3a3a","FTM":"#ff3d3d","FTA":"#ff2121","FT%":"#96ff96","3PTM":"#00ff00","3PTA":"#00ff00","3PT%":"#00ff00","Z":"#ffffff"},{"R":null,"Fantasy Team":"ATL Braves","Name":"Cade Cunningham","Pos":"PG","Team":"DET","GP":"#ffffff","MPG":"#ffffff","PTS":"#ffffff","AST":"#ffffff","REB":"#ffffff","STL":"#ffffff","BLK":"#ffffff","TO":"#ffffff","FGM":"#ffffff","FGA":"#ffffff","FG%":"#ffffff","FTM":"#ffffff","FTA":"#ffffff","FT%":"#ffffff","3PTM":"#ffffff","3PTA":"#ffffff","3PT%":"#ffffff","Z":"#ffffff"},{"R":36.0,"Fantasy Team":"ATL Braves","Name":"John Collins","Pos":"PF","Team":"ATL","GP":"#ff8484","MPG":"#b2ffb2","PTS":"#b2ffb2","AST":"#ff2828","REB":"#0cff0c","STL":"#ff0000","BLK":"#30ff30","TO":"#c1ffc1","FGM":"#60ff60","FGA":"#fcfffc","FG%":"#00ff00","FTM":"#ffeaea","FTA":"#feeded","FT%":"#ffeaea","3PTM":"#ff6868","3PTA":"#ff5e5e","3PT%":"#7cff7c","Z":"#75ff75"},{"R":null,"Fantasy Team":"ATL Braves","Name":"Jalen Green","Pos":"SG","Team":"HOU","GP":"#ffffff","MPG":"#ffffff","PTS":"#ffffff","AST":"#ffffff","REB":"#ffffff","STL":"#ffffff","BLK":"#ffffff","TO":"#ffffff","FGM":"#ffffff","FGA":"#ffffff","FG%":"#ffffff","FTM":"#ffffff","FTA":"#ffffff","FT%":"#ffffff","3PTM":"#ffffff","3PTA":"#ffffff","3PT%":"#ffffff","Z":"#ffffff"},{"R":122.0,"Fantasy Team":"ATL Braves","Name":"Kevin Porter Jr.","Pos":"SG","Team":"HOU","GP":"#ff0000","MPG":"#ff3a3a","PTS":"#ff1111","AST":"#ff6b6b","REB":"#ff2b2b","STL":"#edfeed","BLK":"#ff4242","TO":"#e8ffe8","FGM":"#ff1111","FGA":"#ff1e1e","FG%":"#ffd6d6","FTM":"#ff3a3a","FTA":"#ff3d3d","FT%":"#fed3d3","3PTM":"#ff8787","3PTA":"#ff9e9e","3PT%":"#ffafaf","Z":"#ff0000"},{"R":56.0,"Fantasy Team":"ATL Braves","Name":"Brook Lopez","Pos":"C","Team":"MIL","GP":"#4fff4f","MPG":"#ff4747","PTS":"#ff4242","AST":"#ff1111","REB":"#ff9393","STL":"#ff0000","BLK":"#00ff00","TO":"#00fe00","FGM":"#ff3838","FGA":"#ff5656","FG%":"#ff8282","FTM":"#ff3030","FTA":"#ff2626","FT%":"#edfeed","3PTM":"#e0ffe0","3PTA":"#a3ffa3","3PT%":"#ff0000","Z":"#ddffdd"},{"R":28.0,"Fantasy Team":"ATL Braves","Name":"Mitchell Robinson","Pos":"C","Team":"NYK","GP":"#e5ffe5","MPG":"#ff2626","PTS":"#ff0000","AST":"#ff0000","REB":"#32ff32","STL":"#ffffff","BLK":"#00ff00","TO":"#00ff00","FGM":"#ff3535","FGA":"#ff0000","FG%":"#00ff00","FTM":"#ff3232","FTA":"#ff7c7c","FT%":"#fe0000","3PTM":"#ff0000","3PTA":"#fe0000","3PT%":"#baffba","Z":"#32ff32"},{"R":35.0,"Fantasy Team":"ATL Braves","Name":"Kelly Oubre Jr.","Pos":"PF","Team":"CHA","GP":"#9bff9b","MPG":"#00ff00","PTS":"#2bff2b","AST":"#ff1919","REB":"#baffba","STL":"#1eff1e","BLK":"#ccffcc","TO":"#84ff84","FGM":"#42ff42","FGA":"#0cff0c","FG%":"#ff6b6b","FTM":"#4fff4f","FTA":"#42ff42","FT%":"#ffe0e0","3PTM":"#32ff32","3PTA":"#00ff00","3PT%":"#ff0a0a","Z":"#5eff5e"},{"R":113.0,"Fantasy Team":"ATL Braves","Name":"Gary Trent Jr.","Pos":"SG","Team":"TOR","GP":"#9bff9b","MPG":"#fe0000","PTS":"#fe0000","AST":"#ff0000","REB":"#ff0000","STL":"#ffc6c6","BLK":"#ff5151","TO":"#00ff00","FGM":"#ff0000","FGA":"#ff0000","FG%":"#ff7575","FTM":"#ff0000","FTA":"#ff0000","FT%":"#eaffea","3PTM":"#d8ffd8","3PTA":"#e5ffe5","3PT%":"#4fff4f","Z":"#ff0000"},{"R":93.0,"Fantasy Team":"ATL Braves","Name":"P.J. Washington","Pos":"PF","Team":"CHA","GP":"#9bff9b","MPG":"#8cff8c","PTS":"#ff7272","AST":"#ff6b6b","REB":"#f9fff9","STL":"#ffc6c6","BLK":"#ccffcc","TO":"#a3ffa3","FGM":"#ff8282","FGA":"#ff8787","FG%":"#fff7f7","FTM":"#ff4444","FTA":"#ff6b6b","FT%":"#ff1c1c","3PTM":"#fef4f4","3PTA":"#ffeaea","3PT%":"#5bff5b","Z":"#ff6868"},{"R":9.0,"Fantasy Team":"Team Belkin","Name":"Giannis Antetokounmpo","Pos":"PF","Team":"MIL","GP":"#05ff05","MPG":"#5bff5b","PTS":"#00ff00","AST":"#1cff1c","REB":"#00ff00","STL":"#54ff54","BLK":"#00ff00","TO":"#ff0000","FGM":"#00fe00","FGA":"#00fe00","FG%":"#00ff00","FTM":"#00fe00","FTA":"#00ff00","FT%":"#ff0000","3PTM":"#ffa5a5","3PTA":"#ffcece","3PT%":"#ff1616","Z":"#00ff00"},{"R":61.5,"Fantasy Team":"Team Belkin","Name":"De'Aaron Fox","Pos":"PG","Team":"SAC","GP":"#ffcece","MPG":"#23ff23","PTS":"#56ff56","AST":"#00ff00","REB":"#ff6868","STL":"#00ff00","BLK":"#ffa5a5","TO":"#ff0000","FGM":"#5bff5b","FGA":"#5eff5e","FG%":"#fff2f2","FTM":"#00ff00","FTA":"#00ff00","FT%":"#ff0c0c","3PTM":"#ff7f7f","3PTA":"#ffa5a5","3PT%":"#ff3838","Z":"#ffffff"},{"R":106.0,"Fantasy Team":"Team Belkin","Name":"Julius Randle","Pos":"PF","Team":"NYK","GP":"#ffcece","MPG":"#66ff66","PTS":"#87ff87","AST":"#ffc9c9","REB":"#00fe00","STL":"#ff6666","BLK":"#ff7575","TO":"#ff0000","FGM":"#6bff6b","FGA":"#68ff68","FG%":"#fff2f2","FTM":"#59ff59","FTA":"#1eff1e","FT%":"#ff0000","3PTM":"#ff4c4c","3PTA":"#ff9b9b","3PT%":"#fe0000","Z":"#ff2d2d"},{"R":22.0,"Fantasy Team":"Team Belkin","Name":"Khris Middleton","Pos":"SF","Team":"MIL","GP":"#e5ffe5","MPG":"#66ff66","PTS":"#00ff00","AST":"#f9fff9","REB":"#ccffcc","STL":"#c1ffc1","BLK":"#ff0000","TO":"#ffbaba","FGM":"#00fe00","FGA":"#00ff00","FG%":"#c9ffc9","FTM":"#5eff5e","FTA":"#9eff9e","FT%":"#00ff00","3PTM":"#00fe00","3PTA":"#0cff0c","3PT%":"#00ff00","Z":"#02ff02"},{"R":59.0,"Fantasy Team":"Team Belkin","Name":"CJ McCollum","Pos":"SG","Team":"POR","GP":"#4fff4f","MPG":"#00ff00","PTS":"#21ff21","AST":"#edfeed","REB":"#ff6666","STL":"#ff8787","BLK":"#ffadad","TO":"#c6ffc6","FGM":"#00ff00","FGA":"#00ff00","FG%":"#ff5959","FTM":"#ff9696","FTA":"#ff9191","FT%":"#fcfffc","3PTM":"#00ff00","3PTA":"#02ff02","3PT%":"#8eff8e","Z":"#f4fef4"},{"R":44.0,"Fantasy Team":"Team Belkin","Name":"Jusuf Nurkic","Pos":"C","Team":"POR","GP":"#ff3a3a","MPG":"#c1ffc1","PTS":"#fff9f9","AST":"#ffc6c6","REB":"#00fe00","STL":"#e2ffe2","BLK":"#00fe00","TO":"#ff6868","FGM":"#d8ffd8","FGA":"#fef4f4","FG%":"#42ff42","FTM":"#8eff8e","FTA":"#6bff6b","FT%":"#ff4444","3PTM":"#fe0000","3PTA":"#ff0000","3PT%":"#ff9696","Z":"#a8ffa8"},{"R":115.0,"Fantasy Team":"Team Belkin","Name":"Jakob Poeltl","Pos":"C","Team":"SAS","GP":"#9bff9b","MPG":"#fe0000","PTS":"#ff0000","AST":"#ff0202","REB":"#ffcece","STL":"#ff0000","BLK":"#14ff14","TO":"#00fe00","FGM":"#fe0000","FGA":"#ff0000","FG%":"#00ff00","FTM":"#ff0000","FTA":"#ff0000","FT%":"#ff0707","3PTM":"#ff0000","3PTA":"#fe0000","3PT%":"#baffba","Z":"#ff0000"},{"R":119.0,"Fantasy Team":"Team Belkin","Name":"Darius Garland","Pos":"PG","Team":"CLE","GP":"#9bff9b","MPG":"#5bff5b","PTS":"#ffe8e8","AST":"#baffba","REB":"#ff0000","STL":"#ff7c7c","BLK":"#fe0000","TO":"#ff1c1c","FGM":"#fef4f4","FGA":"#a8ffa8","FG%":"#ff0000","FTM":"#ff6d6d","FTA":"#ff4747","FT%":"#51ff51","3PTM":"#5eff5e","3PTA":"#47ff47","3PT%":"#ffffff","Z":"#ff0000"},{"R":109.0,"Fantasy Team":"Team Belkin","Name":"Caris LeVert","Pos":"SG","Team":"IND","GP":"#ffcece","MPG":"#c1ffc1","PTS":"#f9fff9","AST":"#9bff9b","REB":"#ff7777","STL":"#3fff3f","BLK":"#ff4949","TO":"#ff8787","FGM":"#eaffea","FGA":"#91ff91","FG%":"#ff0000","FTM":"#ffe0e0","FTA":"#f4fef4","FT%":"#ff1616","3PTM":"#f7fff7","3PTA":"#e0ffe0","3PT%":"#ffc4c4","Z":"#ff1c1c"},{"R":77.5,"Fantasy Team":"Team Belkin","Name":"Dennis Schroder","Pos":"PG","Team":"BOS","GP":"#00ff00","MPG":"#f7fff7","PTS":"#afffaf","AST":"#00ff00","REB":"#ff4949","STL":"#ff9191","BLK":"#ff2626","TO":"#ff7070","FGM":"#8eff8e","FGA":"#59ff59","FG%":"#ff7777","FTM":"#ffffff","FTA":"#ffe5e5","FT%":"#8cff8c","3PTM":"#e0ffe0","3PTA":"#c6ffc6","3PT%":"#ffbcbc","Z":"#ffaaaa"},{"R":79.0,"Fantasy Team":"Team Belkin","Name":"Devonte' Graham","Pos":"PG","Team":"NOP","GP":"#9bff9b","MPG":"#49ff49","PTS":"#e2ffe2","AST":"#00ff00","REB":"#ff2121","STL":"#ffc6c6","BLK":"#ff1e1e","TO":"#ff3535","FGM":"#ffcece","FGA":"#a3ffa3","FG%":"#ff0000","FTM":"#fff9f9","FTA":"#ffeaea","FT%":"#c1ffc1","3PTM":"#00ff00","3PTA":"#00fe00","3PT%":"#ffe5e5","Z":"#ffa8a8"},{"R":74.0,"Fantasy Team":"Team Belkin","Name":"Ivica Zubac","Pos":"C","Team":"LAC","GP":"#00ff00","MPG":"#ff0000","PTS":"#ff2121","AST":"#ff0a0a","REB":"#00ff00","STL":"#ff0000","BLK":"#00ff00","TO":"#00ff00","FGM":"#ff4444","FGA":"#ff0000","FG%":"#00ff00","FTM":"#ffa0a0","FTA":"#ffa8a8","FT%":"#ffbfbf","3PTM":"#ff0000","3PTA":"#fe0000","3PT%":"#baffba","Z":"#ffbcbc"},{"R":111.0,"Fantasy Team":"Team Belkin","Name":"Will Barton","Pos":"SF","Team":"DEN","GP":"#ff0000","MPG":"#ffbcbc","PTS":"#ff4747","AST":"#ffc1c1","REB":"#ff7f7f","STL":"#ff0f0f","BLK":"#ff9999","TO":"#5eff5e","FGM":"#ff4747","FGA":"#ff7272","FG%":"#ff5454","FTM":"#ff3a3a","FTA":"#ff3232","FT%":"#fcfffc","3PTM":"#ffeaea","3PTA":"#fff9f9","3PT%":"#ffcece","Z":"#ff0202"},{"R":88.0,"Fantasy Team":"Team Belkin","Name":"Matisse Thybulle","Pos":"SF","Team":"PHL","GP":"#e5ffe5","MPG":"#ff0000","PTS":"#fe0000","AST":"#ff1616","REB":"#ff0000","STL":"#00ff00","BLK":"#a3ffa3","TO":"#00ff00","FGM":"#ff0000","FGA":"#ff0000","FG%":"#ff6b6b","FTM":"#ff0000","FTA":"#ff0000","FT%":"#ff7a7a","3PTM":"#ffc6c6","3PTA":"#ffdbdb","3PT%":"#ffd8d8","Z":"#ff7c7c"},{"R":91.0,"Fantasy Team":"Team Belkin","Name":"Dewayne Dedmon","Pos":"C","Team":"MIA","GP":"#ff3a3a","MPG":"#ff0000","PTS":"#ff0000","AST":"#ff0000","REB":"#91ff91","STL":"#ff9b9b","BLK":"#63ff63","TO":"#2dff2d","FGM":"#ff0000","FGA":"#ff0000","FG%":"#fff9f9","FTM":"#ff0000","FTA":"#ff0000","FT%":"#e0ffe0","3PTM":"#ff3d3d","3PTA":"#ff6b6b","3PT%":"#ff0707","Z":"#ff7272"},{"R":11.0,"Fantasy Team":"Team Trivedi","Name":"Luka Doncic","Pos":"PG","Team":"DAL","GP":"#4fff4f","MPG":"#00ff00","PTS":"#00ff00","AST":"#00ff00","REB":"#00ff00","STL":"#60ff60","BLK":"#ff5151","TO":"#fe0000","FGM":"#00ff00","FGA":"#00ff00","FG%":"#feeded","FTM":"#00fe00","FTA":"#00ff00","FT%":"#ff7777","3PTM":"#00fe00","3PTA":"#00fe00","3PT%":"#ff0000","Z":"#00ff00"},{"R":24.0,"Fantasy Team":"Team Trivedi","Name":"Nikola Vucevic","Pos":"C","Team":"CHI","GP":"#ff8484","MPG":"#b2ffb2","PTS":"#afffaf","AST":"#fff7f7","REB":"#00ff00","STL":"#ffa8a8","BLK":"#87ff87","TO":"#87ff87","FGM":"#35ff35","FGA":"#51ff51","FG%":"#91ff91","FTM":"#ff6d6d","FTA":"#ff6868","FT%":"#fcfffc","3PTM":"#ff9b9b","3PTA":"#ffbcbc","3PT%":"#ff6666","Z":"#14ff14"},{"R":54.5,"Fantasy Team":"Team Trivedi","Name":"Zion Williamson","Pos":"PF","Team":"NOP","GP":"#ff3a3a","MPG":"#7fff7f","PTS":"#00ff00","AST":"#ff6666","REB":"#21ff21","STL":"#a0ffa0","BLK":"#b7ffb7","TO":"#ff3232","FGM":"#00ff00","FGA":"#0fff0f","FG%":"#00fe00","FTM":"#00ff00","FTA":"#00ff00","FT%":"#ff0000","3PTM":"#ff0000","3PTA":"#ff0000","3PT%":"#b2ffb2","Z":"#dbffdb"},{"R":61.5,"Fantasy Team":"Team Trivedi","Name":"Dejounte Murray","Pos":"PG","Team":"SAS","GP":"#e5ffe5","MPG":"#ff6b6b","PTS":"#ff1c1c","AST":"#b5feb5","REB":"#baffba","STL":"#00ff00","BLK":"#ff7a7a","TO":"#fef4f4","FGM":"#ff5151","FGA":"#ff5656","FG%":"#fff7f7","FTM":"#ff2121","FTA":"#ff2121","FT%":"#ffe5e5","3PTM":"#ff0000","3PTA":"#ff0000","3PT%":"#e0ffe0","Z":"#ffffff"},{"R":38.0,"Fantasy Team":"Team Trivedi","Name":"DeMar DeRozan","Pos":"SG","Team":"CHI","GP":"#00ff00","MPG":"#1eff1e","PTS":"#00ff00","AST":"#00ff00","REB":"#ffffff","STL":"#d6ffd6","BLK":"#ff5151","TO":"#ff7070","FGM":"#00ff00","FGA":"#00ff00","FG%":"#42ff42","FTM":"#00fe00","FTA":"#00ff00","FT%":"#00ff00","3PTM":"#ff0000","3PTA":"#fe0000","3PT%":"#ff7575","Z":"#7fff7f"},{"R":103.5,"Fantasy Team":"Team Trivedi","Name":"Collin Sexton","Pos":"SG","Team":"CLE","GP":"#4fff4f","MPG":"#19ff19","PTS":"#60ff60","AST":"#ffcece","REB":"#ff1c1c","STL":"#ffc6c6","BLK":"#fe0000","TO":"#ff6868","FGM":"#30ff30","FGA":"#05ff05","FG%":"#ff6868","FTM":"#bfffbf","FTA":"#e0ffe0","FT%":"#5bff5b","3PTM":"#fffcfc","3PTA":"#ffefef","3PT%":"#59ff59","Z":"#ff3a3a"},{"R":84.0,"Fantasy Team":"Team Trivedi","Name":"Jarrett Allen","Pos":"C","Team":"CLE","GP":"#e5ffe5","MPG":"#ff2626","PTS":"#ff0f0f","AST":"#fe0000","REB":"#00ff00","STL":"#ff0000","BLK":"#00ff00","TO":"#0aff0a","FGM":"#ff2323","FGA":"#fe0000","FG%":"#00ff00","FTM":"#ffa0a0","FTA":"#ffd8d8","FT%":"#fe0000","3PTM":"#ff0000","3PTA":"#ff0000","3PT%":"#ffcece","Z":"#ff8e8e"},{"R":64.0,"Fantasy Team":"Team Trivedi","Name":"Tyrese Haliburton","Pos":"PG","Team":"SAC","GP":"#4fff4f","MPG":"#ffadad","PTS":"#ff5454","AST":"#26ff26","REB":"#ffbaba","STL":"#00ff00","BLK":"#ff7a7a","TO":"#ff6868","FGM":"#ff3535","FGA":"#ff5656","FG%":"#ff8282","FTM":"#ff6b6b","FTA":"#ff5656","FT%":"#b5feb5","3PTM":"#ccffcc","3PTA":"#ff0a0a","3PT%":"#fef4f4","Z":"#fffcfc"},{"R":126.0,"Fantasy Team":"Team Trivedi","Name":"Isaiah Stewart","Pos":"C","Team":"DET","GP":"#ff3a3a","MPG":"#ff0000","PTS":"#ff0000","AST":"#ff0000","REB":"#ffa8a8","STL":"#ff0000","BLK":"#8cff8c","TO":"#68ff68","FGM":"#ff0000","FGA":"#fe0000","FG%":"#b7ffb7","FTM":"#ff9999","FTA":"#ff9999","FT%":"#ffefef","3PTM":"#fe0000","3PTA":"#ff0000","3PT%":"#bcffbc","Z":"#ff0000"},{"R":98.0,"Fantasy Team":"Team Trivedi","Name":"Bogdan Bogdanovic","Pos":"SG","Team":"ATL","GP":"#9bff9b","MPG":"#ffc1c1","PTS":"#ff9e9e","AST":"#fff7f7","REB":"#ff2121","STL":"#f7fff7","BLK":"#ff1e1e","TO":"#a3ffa3","FGM":"#ff9b9b","FGA":"#ffd8d8","FG%":"#ff3535","FTM":"#ff3f3f","FTA":"#ff3a3a","FT%":"#fff2f2","3PTM":"#5eff5e","3PTA":"#47ff47","3PT%":"#ff9999","Z":"#ff5454"},{"R":null,"Fantasy Team":"Team Trivedi","Name":"Jonathan Isaac","Pos":"PF","Team":"ORL","GP":"#ffffff","MPG":"#ffffff","PTS":"#ffffff","AST":"#ffffff","REB":"#ffffff","STL":"#ffffff","BLK":"#ffffff","TO":"#ffffff","FGM":"#ffffff","FGA":"#ffffff","FG%":"#ffffff","FTM":"#ffffff","FTA":"#ffffff","FT%":"#ffffff","3PTM":"#ffffff","3PTA":"#ffffff","3PT%":"#ffffff","Z":"#ffffff"},{"R":129.0,"Fantasy Team":"Team Trivedi","Name":"Reggie Jackson","Pos":"PG","Team":"LAC","GP":"#ff0000","MPG":"#ff0000","PTS":"#ff0000","AST":"#ffc9c9","REB":"#ff0000","STL":"#ff0000","BLK":"#ff0000","TO":"#28ff28","FGM":"#ff0000","FGA":"#ff0f0f","FG%":"#ff4f4f","FTM":"#ff3030","FTA":"#ff1919","FT%":"#a8ffa8","3PTM":"#ffb2b2","3PTA":"#ffbaba","3PT%":"#e2ffe2","Z":"#fe0000"},{"R":73.0,"Fantasy Team":"Team Trivedi","Name":"Ricky Rubio","Pos":"PG","Team":"CLE","GP":"#ffcece","MPG":"#ffffff","PTS":"#ff5656","AST":"#00ff00","REB":"#ff7070","STL":"#00ff00","BLK":"#ff1e1e","TO":"#ff5151","FGM":"#ff3030","FGA":"#ff7a7a","FG%":"#ff0000","FTM":"#ffe5e5","FTA":"#ffc6c6","FT%":"#60ff60","3PTM":"#ff8282","3PTA":"#ffa5a5","3PT%":"#ff7272","Z":"#ffbfbf"},{"R":120.5,"Fantasy Team":"Team Trivedi","Name":"De'Anthony Melton","Pos":"PG","Team":"MEM","GP":"#ff0000","MPG":"#fe0000","PTS":"#ff0000","AST":"#ffa5a5","REB":"#ff0c0c","STL":"#75ff75","BLK":"#ff6d6d","TO":"#3fff3f","FGM":"#ff0000","FGA":"#fe0000","FG%":"#ff7272","FTM":"#ff0000","FTA":"#ff0000","FT%":"#e8ffe8","3PTM":"#ff0000","3PTA":"#ff1111","3PT%":"#ff8e8e","Z":"#ff0000"},{"R":100.5,"Fantasy Team":"Team Trivedi","Name":"Joe Harris","Pos":"SG","Team":"BKN","GP":"#ffcece","MPG":"#dbffdb","PTS":"#ff7a7a","AST":"#ff5959","REB":"#ff6868","STL":"#ff0000","BLK":"#ff4949","TO":"#5bff5b","FGM":"#ff7f7f","FGA":"#ff7070","FG%":"#e0ffe0","FTM":"#ff0000","FTA":"#ff0000","FT%":"#ffffff","3PTM":"#49ff49","3PTA":"#93ff93","3PT%":"#00ff00","Z":"#ff4747"},{"R":6.0,"Fantasy Team":"UCLA Bruins","Name":"Damian Lillard","Pos":"PG","Team":"POR","GP":"#9bff9b","MPG":"#00ff00","PTS":"#00fe00","AST":"#00ff00","REB":"#ff7c7c","STL":"#f7fff7","BLK":"#ff5151","TO":"#ff0000","FGM":"#00ff00","FGA":"#00fe00","FG%":"#ff4444","FTM":"#00fe00","FTA":"#00ff00","FT%":"#00ff00","3PTM":"#00ff00","3PTA":"#00fe00","3PT%":"#00fe00","Z":"#00ff00"},{"R":15.0,"Fantasy Team":"UCLA Bruins","Name":"Joel Embiid","Pos":"C","Team":"PHL","GP":"#ff8484","MPG":"#8cff8c","PTS":"#00ff00","AST":"#ffd8d8","REB":"#00ff00","STL":"#ff6666","BLK":"#00ff00","TO":"#fe0000","FGM":"#11ff11","FGA":"#19ff19","FG%":"#ccffcc","FTM":"#00ff00","FTA":"#00ff00","FT%":"#adffad","3PTM":"#ff8e8e","3PTA":"#ffc4c4","3PT%":"#ff0000","Z":"#00fe00"},{"R":29.5,"Fantasy Team":"UCLA Bruins","Name":"Bam Adebayo","Pos":"C","Team":"MIA","GP":"#00ff00","MPG":"#9bff9b","PTS":"#edfeed","AST":"#bcffbc","REB":"#00ff00","STL":"#8cff8c","BLK":"#00ff00","TO":"#ff7070","FGM":"#afffaf","FGA":"#ffc9c9","FG%":"#00fe00","FTM":"#9eff9e","FTA":"#70ff70","FT%":"#ff1e1e","3PTM":"#ff0000","3PTA":"#ff0000","3PT%":"#e8ffe8","Z":"#3fff3f"},{"R":29.5,"Fantasy Team":"UCLA Bruins","Name":"Jrue Holiday","Pos":"PG","Team":"MIL","GP":"#9bff9b","MPG":"#00ff00","PTS":"#77ff77","AST":"#00ff00","REB":"#ffaaaa","STL":"#00ff00","BLK":"#ccffcc","TO":"#ff0000","FGM":"#2bff2b","FGA":"#19ff19","FG%":"#fff2f2","FTM":"#ffbfbf","FTA":"#fed3d3","FT%":"#ff8282","3PTM":"#c4ffc4","3PTA":"#96ff96","3PT%":"#fe0000","Z":"#3fff3f"},{"R":86.0,"Fantasy Team":"UCLA Bruins","Name":"Andrew Wiggins","Pos":"SF","Team":"GSW","GP":"#05ff05","MPG":"#3fff3f","PTS":"#c4ffc4","AST":"#ffafaf","REB":"#ffadad","STL":"#fed3d3","BLK":"#bfffbf","TO":"#fef4f4","FGM":"#bcffbc","FGA":"#96ff96","FG%":"#ff7f7f","FTM":"#d1ffd1","FTA":"#b5feb5","FT%":"#ff7f7f","3PTM":"#ffffff","3PTA":"#ccffcc","3PT%":"#ff1919","Z":"#ff8989"},{"R":13.0,"Fantasy Team":"UCLA Bruins","Name":"Kyrie Irving","Pos":"PG","Team":"BKN","GP":"#ff0000","MPG":"#75ff75","PTS":"#00ff00","AST":"#00fe00","REB":"#ff8787","STL":"#28ff28","BLK":"#ff4242","TO":"#ffadad","FGM":"#00ff00","FGA":"#00ff00","FG%":"#c9ffc9","FTM":"#bcffbc","FTA":"#f4fef4","FT%":"#00ff00","3PTM":"#26ff26","3PTA":"#49ff49","3PT%":"#00ff00","Z":"#00fe00"},{"R":42.0,"Fantasy Team":"UCLA Bruins","Name":"Gordon Hayward","Pos":"SF","Team":"CHA","GP":"#ff0000","MPG":"#19ff19","PTS":"#91ff91","AST":"#d3fed3","REB":"#efffef","STL":"#ff9191","BLK":"#ff6d6d","TO":"#afffaf","FGM":"#82ff82","FGA":"#9eff9e","FG%":"#99ff99","FTM":"#baffba","FTA":"#d6ffd6","FT%":"#59ff59","3PTM":"#dbffdb","3PTA":"#d1ffd1","3PT%":"#efffef","Z":"#9bff9b"},{"R":49.5,"Fantasy Team":"UCLA Bruins","Name":"Draymond Green","Pos":"PF","Team":"GSW","GP":"#e5ffe5","MPG":"#8cff8c","PTS":"#ff0000","AST":"#00ff00","REB":"#72ff72","STL":"#00ff00","BLK":"#77ff77","TO":"#ff4444","FGM":"#ff0000","FGA":"#ff0000","FG%":"#ff9e9e","FTM":"#ff2626","FTA":"#ff2b2b","FT%":"#ffb7b7","3PTM":"#ff5656","3PTA":"#ff8c8c","3PT%":"#ff0000","Z":"#c1ffc1"},{"R":61.5,"Fantasy Team":"UCLA Bruins","Name":"Marcus Smart","Pos":"SG","Team":"BOS","GP":"#ff8484","MPG":"#8cff8c","PTS":"#ff3d3d","AST":"#82ff82","REB":"#ff3535","STL":"#00fe00","BLK":"#ff9e9e","TO":"#a8ffa8","FGM":"#ff0f0f","FGA":"#ff7575","FG%":"#ff0000","FTM":"#ff5454","FTA":"#ff4747","FT%":"#c9ffc9","3PTM":"#89ff89","3PTA":"#59ff59","3PT%":"#ff3838","Z":"#ffffff"},{"R":null,"Fantasy Team":"UCLA Bruins","Name":"Jalen Suggs","Pos":"PG","Team":"ORL","GP":"#ffffff","MPG":"#ffffff","PTS":"#ffffff","AST":"#ffffff","REB":"#ffffff","STL":"#ffffff","BLK":"#ffffff","TO":"#ffffff","FGM":"#ffffff","FGA":"#ffffff","FG%":"#ffffff","FTM":"#ffffff","FTA":"#ffffff","FT%":"#ffffff","3PTM":"#ffffff","3PTA":"#ffffff","3PT%":"#ffffff","Z":"#ffffff"},{"R":94.5,"Fantasy Team":"UCLA Bruins","Name":"Seth Curry","Pos":"SG","Team":"PHL","GP":"#9bff9b","MPG":"#ff7777","PTS":"#ff7575","AST":"#ff3d3d","REB":"#ff0000","STL":"#ff3a3a","BLK":"#ff1e1e","TO":"#0cff0c","FGM":"#ff6868","FGA":"#ff5454","FG%":"#baffba","FTM":"#ff0a0a","FTA":"#fe0000","FT%":"#c4ffc4","3PTM":"#23ff23","3PTA":"#8cff8c","3PT%":"#00ff00","Z":"#ff6666"},{"R":97.0,"Fantasy Team":"UCLA Bruins","Name":"Jae Crowder","Pos":"PF","Team":"PHO","GP":"#05ff05","MPG":"#fed3d3","PTS":"#ff3535","AST":"#ff5b5b","REB":"#ffefef","STL":"#e2ffe2","BLK":"#ff8282","TO":"#00ff00","FGM":"#ff0202","FGA":"#ff5e5e","FG%":"#ff0000","FTM":"#ff5959","FTA":"#ff5b5b","FT%":"#ffcccc","3PTM":"#8cff8c","3PTA":"#35ff35","3PT%":"#ff0000","Z":"#ff5b5b"},{"R":102.0,"Fantasy Team":"UCLA Bruins","Name":"Kentavious Caldwell-Pope","Pos":"SG","Team":"WAS","GP":"#00ff00","MPG":"#ff3535","PTS":"#ff2626","AST":"#ff2323","REB":"#ff0707","STL":"#d6ffd6","BLK":"#ff2626","TO":"#00ff00","FGM":"#ff0f0f","FGA":"#ff2626","FG%":"#ffb2b2","FTM":"#ff3030","FTA":"#ff2121","FT%":"#e0ffe0","3PTM":"#e0ffe0","3PTA":"#dbffdb","3PT%":"#edfeed","Z":"#ff4242"},{"R":82.0,"Fantasy Team":"UCLA Bruins","Name":"Justin Holiday","Pos":"SG","Team":"IND","GP":"#4fff4f","MPG":"#ff9696","PTS":"#ff0000","AST":"#ff1e1e","REB":"#ff4242","STL":"#14ff14","BLK":"#ffadad","TO":"#00fe00","FGM":"#fe0000","FGA":"#ff0505","FG%":"#ff3030","FTM":"#ff0000","FTA":"#ff0000","FT%":"#d6ffd6","3PTM":"#a5ffa5","3PTA":"#aaffaa","3PT%":"#9bff9b","Z":"#ff9393"},{"R":116.0,"Fantasy Team":"UCLA Bruins","Name":"Luke Kennard","Pos":"SG","Team":"LAC","GP":"#ff0000","MPG":"#ffcece","PTS":"#ff2626","AST":"#ff8787","REB":"#ff0202","STL":"#ff0000","BLK":"#ff1111","TO":"#00ff00","FGM":"#ff1414","FGA":"#ff3030","FG%":"#ff8c8c","FTM":"#ff1919","FTA":"#ff0000","FT%":"#9bff9b","3PTM":"#c4ffc4","3PTA":"#e0ffe0","3PT%":"#00ff00","Z":"#ff0000"},{"R":5.0,"Fantasy Team":"Gay for Oubre","Name":"Stephen Curry","Pos":"PG","Team":"GSW","GP":"#ff8484","MPG":"#70ff70","PTS":"#00ff00","AST":"#2bff2b","REB":"#ffb7b7","STL":"#00fe00","BLK":"#ff4949","TO":"#ff2323","FGM":"#00ff00","FGA":"#00ff00","FG%":"#c9ffc9","FTM":"#28ff28","FTA":"#82ff82","FT%":"#00ff00","3PTM":"#00ff00","3PTA":"#00ff00","3PT%":"#00ff00","Z":"#00ff00"},{"R":33.0,"Fantasy Team":"Gay for Oubre","Name":"Fred VanVleet","Pos":"SG","Team":"TOR","GP":"#9bff9b","MPG":"#23ff23","PTS":"#d1ffd1","AST":"#00fe00","REB":"#ff3a3a","STL":"#00fe00","BLK":"#ff5151","TO":"#ffe8e8","FGM":"#ffffff","FGA":"#8cff8c","FG%":"#ff0000","FTM":"#e0ffe0","FTA":"#ffffff","FT%":"#66ff66","3PTM":"#11ff11","3PTA":"#21ff21","3PT%":"#21ff21","Z":"#56ff56"},{"R":17.0,"Fantasy Team":"Gay for Oubre","Name":"Shai Gilgeous-Alexander","Pos":"SG","Team":"OKC","GP":"#e5ffe5","MPG":"#00ff00","PTS":"#16ff16","AST":"#16ff16","REB":"#ddffdd","STL":"#75ff75","BLK":"#d3fed3","TO":"#efffef","FGM":"#0fff0f","FGA":"#11ff11","FG%":"#ccffcc","FTM":"#05ff05","FTA":"#14ff14","FT%":"#9eff9e","3PTM":"#fff9f9","3PTA":"#f4fef4","3PT%":"#ffc9c9","Z":"#00ff00"},{"R":27.0,"Fantasy Team":"Gay for Oubre","Name":"Brandon Ingram","Pos":"SF","Team":"NOP","GP":"#9bff9b","MPG":"#2bff2b","PTS":"#00ff00","AST":"#baffba","REB":"#ddffdd","STL":"#ffc6c6","BLK":"#f7fff7","TO":"#ff0000","FGM":"#00ff00","FGA":"#00ff00","FG%":"#ffefef","FTM":"#00ff00","FTA":"#00ff00","FT%":"#0cff0c","3PTM":"#11ff11","3PTA":"#21ff21","3PT%":"#21ff21","Z":"#28ff28"},{"R":92.0,"Fantasy Team":"Gay for Oubre","Name":"OG Anunoby","Pos":"SF","Team":"TOR","GP":"#4fff4f","MPG":"#ffbcbc","PTS":"#ff0000","AST":"#ff0000","REB":"#ffafaf","STL":"#60ff60","BLK":"#ffadad","TO":"#00fe00","FGM":"#ff0f0f","FGA":"#ff0000","FG%":"#c6ffc6","FTM":"#ff0000","FTA":"#ff0000","FT%":"#ff7272","3PTM":"#feb5b5","3PTA":"#ffbfbf","3PT%":"#e2ffe2","Z":"#ff7070"},{"R":57.0,"Fantasy Team":"Gay for Oubre","Name":"Myles Turner","Pos":"C","Team":"IND","GP":"#ff0000","MPG":"#ffe2e2","PTS":"#ff3838","AST":"#ff0000","REB":"#c6ffc6","STL":"#ff5151","BLK":"#00fe00","TO":"#0cff0c","FGM":"#ff3838","FGA":"#ff3838","FG%":"#fff9f9","FTM":"#ff6b6b","FTA":"#ff7272","FT%":"#feb5b5","3PTM":"#ff7a7a","3PTA":"#ff8c8c","3PT%":"#ffb7b7","Z":"#e0ffe0"},{"R":20.0,"Fantasy Team":"Gay for Oubre","Name":"Pascal Siakam","Pos":"PF","Team":"TOR","GP":"#4fff4f","MPG":"#00ff00","PTS":"#00ff00","AST":"#fffcfc","REB":"#11ff11","STL":"#a0ffa0","BLK":"#6bff6b","TO":"#ff8787","FGM":"#00ff00","FGA":"#00ff00","FG%":"#ffefef","FTM":"#00ff00","FTA":"#00fe00","FT%":"#f7fff7","3PTM":"#adffad","3PTA":"#8eff8e","3PT%":"#ffadad","Z":"#00ff00"},{"R":68.0,"Fantasy Team":"Gay for Oubre","Name":"Kemba Walker","Pos":"PG","Team":"NYK","GP":"#ff0000","MPG":"#ffffff","PTS":"#ccffcc","AST":"#b7ffb7","REB":"#ff0f0f","STL":"#ffa8a8","BLK":"#ff5e5e","TO":"#c1ffc1","FGM":"#f9fff9","FGA":"#adffad","FG%":"#ff1111","FTM":"#ceffce","FTA":"#f4fef4","FT%":"#28ff28","3PTM":"#2bff2b","3PTA":"#1cff1c","3PT%":"#fffcfc","Z":"#ffd8d8"},{"R":16.0,"Fantasy Team":"Gay for Oubre","Name":"Robert Covington","Pos":"PF","Team":"POR","GP":"#05ff05","MPG":"#8cff8c","PTS":"#ffc6c6","AST":"#ff0000","REB":"#93ff93","STL":"#00ff00","BLK":"#00ff00","TO":"#91ff91","FGM":"#ffa8a8","FGA":"#ffe2e2","FG%":"#ff3232","FTM":"#ff6666","FTA":"#ff5b5b","FT%":"#eaffea","3PTM":"#00ff00","3PTA":"#00ff00","3PT%":"#ff0000","Z":"#00ff00"},{"R":77.5,"Fantasy Team":"Gay for Oubre","Name":"Evan Fournier","Pos":"SG","Team":"NYK","GP":"#9bff9b","MPG":"#b2ffb2","PTS":"#e5ffe5","AST":"#ffe0e0","REB":"#ff0000","STL":"#f7fff7","BLK":"#ff1e1e","TO":"#ddffdd","FGM":"#e0ffe0","FGA":"#c6ffc6","FG%":"#ffbfbf","FTM":"#ffaaaa","FTA":"#ff9999","FT%":"#b7ffb7","3PTM":"#42ff42","3PTA":"#47ff47","3PT%":"#93ff93","Z":"#ffaaaa"},{"R":120.5,"Fantasy Team":"Gay for Oubre","Name":"T.J. McConnell","Pos":"PG","Team":"IND","GP":"#4fff4f","MPG":"#ff0000","PTS":"#ff0000","AST":"#a5ffa5","REB":"#ff0000","STL":"#ffc6c6","BLK":"#ff1e1e","TO":"#32ff32","FGM":"#ff0000","FGA":"#ff0000","FG%":"#91ff91","FTM":"#ff0000","FTA":"#ff0000","FT%":"#f7fff7","3PTM":"#fe0000","3PTA":"#ff0000","3PT%":"#c4ffc4","Z":"#ff0000"},{"R":114.0,"Fantasy Team":"Gay for Oubre","Name":"Saddiq Bey","Pos":"SF","Team":"DET","GP":"#ff3a3a","MPG":"#ff0000","PTS":"#ff0000","AST":"#ff1919","REB":"#ff3030","STL":"#ff9b9b","BLK":"#e2ffe2","TO":"#00ff00","FGM":"#ff0000","FGA":"#ff0000","FG%":"#ffc9c9","FTM":"#ff0000","FTA":"#fe0000","FT%":"#ffeaea","3PTM":"#ff4444","3PTA":"#ff0000","3PT%":"#f2fff2","Z":"#ff0000"},{"R":37.0,"Fantasy Team":"Gay for Oubre","Name":"Andre Drummond","Pos":"C","Team":"PHL","GP":"#05ff05","MPG":"#8cff8c","PTS":"#efffef","AST":"#ff6666","REB":"#00ff00","STL":"#00ff00","BLK":"#00fe00","TO":"#ff0000","FGM":"#8cff8c","FGA":"#e8ffe8","FG%":"#00ff00","FTM":"#fcfffc","FTA":"#60ff60","FT%":"#ff0000","3PTM":"#ff0000","3PTA":"#ff0000","3PT%":"#ff6d6d","Z":"#7cff7c"},{"R":83.0,"Fantasy Team":"Gay for Oubre","Name":"Joe Ingles","Pos":"SF","Team":"UTA","GP":"#00ff00","MPG":"#e8ffe8","PTS":"#ff2323","AST":"#1eff1e","REB":"#ff7070","STL":"#d6ffd6","BLK":"#ff2626","TO":"#ffcccc","FGM":"#ff0f0f","FGA":"#ff2626","FG%":"#ffb2b2","FTM":"#fe0000","FTA":"#ff0000","FT%":"#ffd8d8","3PTM":"#66ff66","3PTA":"#87ff87","3PT%":"#00ff00","Z":"#ff9191"}]